LICENSE.txt
README.md
setup.cfg
setup.py
relbert/__init__.py
relbert/list_keeper.py
relbert/lm.py
relbert/trainer.py
relbert/util.py
relbert.egg-info/PKG-INFO
relbert.egg-info/SOURCES.txt
relbert.egg-info/dependency_links.txt
relbert.egg-info/entry_points.txt
relbert.egg-info/requires.txt
relbert.egg-info/top_level.txt
relbert/evaluation/__init__.py
relbert/evaluation/analogy_questions.py
relbert/evaluation/lexical_relation_classification.py
relbert/evaluation/relation_mapping.py
relbert/relbert_cl/__init__.py
relbert/relbert_cl/evaluate.py
relbert/relbert_cl/push_to_hub.py
relbert/relbert_cl/readme_template.py
relbert/relbert_cl/train.py