Metadata-Version: 2.1
Name: relbert
Version: 2.0.0
Summary: RelBERT: the state-of-the-art lexical relation embedding model.
Home-page: https://github.com/asahi417/relbert
Author: Asahi Ushio
Author-email: asahi1992ushio@gmail.com
License: MIT
Download-URL: https://github.com/asahi417/relbert/archive/v2.0.0.tar.gz
Keywords: nlp
Platform: UNKNOWN
Classifier: Development Status :: 4 - Beta
Classifier: Intended Audience :: Developers
Classifier: Intended Audience :: Science/Research
Classifier: Topic :: Scientific/Engineering
Classifier: License :: OSI Approved :: MIT License
Classifier: Programming Language :: Python :: 3
Requires-Python: >=3.6
Provides-Extra: visualization
License-File: LICENSE.txt
